KaggleAPIConnection.py
kaggle_st_connection-1.3.3.dist-info/LICENSE
kaggle_st_connection-1.3.3.dist-info/METADATA
kaggle_st_connection-1.3.3.dist-info/WHEEL
kaggle_st_connection-1.3.3.dist-info/top_level.txt
kaggle_st_connection-1.3.3.dist-info/RECORD
